README.md
setup.py
pulumi_fivetran/__init__.py
pulumi_fivetran/_inputs.py
pulumi_fivetran/_utilities.py
pulumi_fivetran/connector.py
pulumi_fivetran/connector_schedule.py
pulumi_fivetran/connector_schema_config.py
pulumi_fivetran/destination.py
pulumi_fivetran/get_connector.py
pulumi_fivetran/get_connectors_metadata.py
pulumi_fivetran/get_destination.py
pulumi_fivetran/get_group.py
pulumi_fivetran/get_group_connectors.py
pulumi_fivetran/get_group_users.py
pulumi_fivetran/get_groups.py
pulumi_fivetran/get_user.py
pulumi_fivetran/get_users.py
pulumi_fivetran/group.py
pulumi_fivetran/group_users.py
pulumi_fivetran/outputs.py
pulumi_fivetran/provider.py
pulumi_fivetran/pulumi-plugin.json
pulumi_fivetran/py.typed
pulumi_fivetran/user.py
pulumi_fivetran.egg-info/PKG-INFO
pulumi_fivetran.egg-info/SOURCES.txt
pulumi_fivetran.egg-info/dependency_links.txt
pulumi_fivetran.egg-info/not-zip-safe
pulumi_fivetran.egg-info/requires.txt
pulumi_fivetran.egg-info/top_level.txt
pulumi_fivetran/config/__init__.py
pulumi_fivetran/config/vars.py