Metadata-Version: 2.1
Name: pulumi-fivetran
Version: 0.1.12
Summary: A Pulumi package for creating and managing Fivetran resources.
Home-page: https://github.com/benesch/pulumi-fivetran
License: Apache-2.0
Project-URL: Repository, https://github.com/benesch/pulumi-fivetran
Keywords: pulumi fivetran
Platform: UNKNOWN
Requires-Python: >=3.7
